[
    {
        "lat": 51.38023888888889,
        "lon": -0.07164722222222222,
        "title": "IMG-2550.jpg"
    },
    {
        "lat": 51.128341666666664,
        "lon": 1.3357638888888888,
        "title": "IMG_1237.JPG"
    },
    {
        "lat": 51.12835,
        "lon": 1.3357694444444443,
        "title": "IMG_1238.JPG"
    },
    {
        "lat": 51.128341666666664,
        "lon": 1.3357694444444443,
        "title": "IMG_1239.JPG"
    },
    {
        "lat": 51.12833888888889,
        "lon": 1.3357722222222221,
        "title": "IMG_1240.JPG"
    },
    {
        "lat": 51.12833333333333,
        "lon": 1.3357833333333333,
        "title": "IMG_1241.JPG"
    },
    {
        "lat": 51.12838055555556,
        "lon": 1.3358333333333332,
        "title": "IMG_1247.JPG"
    },
    {
        "lat": 51.12838055555556,
        "lon": 1.3358444444444444,
        "title": "IMG_1248.JPG"
    },
    {
        "lat": 51.12838055555556,
        "lon": 1.3358305555555554,
        "title": "IMG_1249.JPG"
    },
    {
        "lat": 51.12838055555556,
        "lon": 1.3358305555555554,
        "title": "IMG_1250.JPG"
    },
    {
        "lat": 51.128375,
        "lon": 1.3358305555555554,
        "title": "IMG_1251.JPG"
    },
    {
        "lat": 51.12836388888889,
        "lon": 1.3358472222222222,
        "title": "IMG_1252.JPG"
    },
    {
        "lat": 51.12836111111111,
        "lon": 1.3358249999999998,
        "title": "IMG_1253.JPG"
    },
    {
        "lat": 51.12836111111111,
        "lon": 1.3358249999999998,
        "title": "IMG_1254.JPG"
    },
    {
        "lat": 51.12838333333333,
        "lon": 1.335797222222222,
        "title": "IMG_1255.JPG"
    },
    {
        "lat": 51.128433333333334,
        "lon": 1.3359277777777776,
        "title": "IMG_1256.JPG"
    },
    {
        "lat": 51.128436111111114,
        "lon": 1.3359305555555554,
        "title": "IMG_1257.JPG"
    },
    {
        "lat": 51.128455555555554,
        "lon": 1.3360166666666666,
        "title": "IMG_1258.JPG"
    },
    {
        "lat": 51.128455555555554,
        "lon": 1.336025,
        "title": "IMG_1259.JPG"
    },
    {
        "lat": 51.12844722222222,
        "lon": 1.3360333333333332,
        "title": "IMG_1260.JPG"
    },
    {
        "lat": 51.128436111111114,
        "lon": 1.3360055555555554,
        "title": "IMG_1261.JPG"
    },
    {
        "lat": 51.128425,
        "lon": 1.3360027777777777,
        "title": "IMG_1262.JPG"
    },
    {
        "lat": 51.12844444444445,
        "lon": 1.3360166666666666,
        "title": "IMG_1263.JPG"
    },
    {
        "lat": 51.128455555555554,
        "lon": 1.3360222222222222,
        "title": "IMG_1264.JPG"
    },
    {
        "lat": 51.12845277777778,
        "lon": 1.3360138888888888,
        "title": "IMG_1265.JPG"
    },
    {
        "lat": 51.128461111111115,
        "lon": 1.3360333333333332,
        "title": "IMG_1266.JPG"
    },
    {
        "lat": 51.12844444444445,
        "lon": 1.3360277777777778,
        "title": "IMG_1267.JPG"
    },
    {
        "lat": 51.128455555555554,
        "lon": 1.3360416666666666,
        "title": "IMG_1268.JPG"
    },
    {
        "lat": 51.12844444444445,
        "lon": 1.3360333333333332,
        "title": "IMG_1269.JPG"
    },
    {
        "lat": 51.12844722222222,
        "lon": 1.3360472222222222,
        "title": "IMG_1270.JPG"
    },
    {
        "lat": 51.12844722222222,
        "lon": 1.3360472222222222,
        "title": "IMG_1271.JPG"
    }
]